pyolive/__init__.py
pyolive/__main__.py
pyolive/adapter.py
pyolive/agent.py
pyolive/app.py
pyolive/channel.py
pyolive/channel_consumer.py
pyolive/channel_publisher.py
pyolive/config.py
pyolive/context.py
pyolive/develop.py
pyolive/filter.py
pyolive/heartbeat.py
pyolive/job_context.py
pyolive/log.py
pyolive/resource_watcher.py
pyolive/status.py
pyolive/utils.py
pyolive/worker.py
pyolive/channel/__init__.py
pyolive/channel/adapter.py
pyolive/channel/consumer.py
pyolive/channel/producer.py
pyolive/db/__init__.py
pyolive/db/base.py
pyolive/db/factory.py
pyolive/db/mysql.py
pyolive/db/postgres.py
pyolive-2.1.4.dist-info/LICENSE.txt
pyolive-2.1.4.dist-info/METADATA
pyolive-2.1.4.dist-info/WHEEL
pyolive-2.1.4.dist-info/top_level.txt
pyolive-2.1.4.dist-info/RECORD
