Metadata-Version: 2.1
Name: pyolive
Version: 2.1.4
Summary: Python API for Athena Worker.
Home-page: http://www.ingris.com
Author: Kiro Lee
Author-email: kiroly@ingris.com
Requires-Python: >=3.9
License-File: LICENSE.txt
Requires-Dist: aio-pika>=9.5.5
Requires-Dist: PyYAML>=6.0.1
Requires-Dist: watchdog>=6.0.0
Requires-Dist: aiomysql>=0.2.0
Requires-Dist: asyncpg>=0.30.0
